flootty/__init__.py
flootty/flootty.py
flootty/version.py
flootty/floo/__init__.py
flootty/floo/editor.py
flootty/floo/common/README.md
flootty/floo/common/__init__.py
flootty/floo/common/api.py
flootty/floo/common/cert.py
flootty/floo/common/event_emitter.py
flootty/floo/common/exc_fmt.py
flootty/floo/common/flooui.py
flootty/floo/common/ignore.py
flootty/floo/common/msg.py
flootty/floo/common/proxy.py
flootty/floo/common/reactor.py
flootty/floo/common/repo.py
flootty/floo/common/shared.py
flootty/floo/common/utils.py
flootty/floo/common/handlers/__init__.py
flootty/floo/common/handlers/account.py
flootty/floo/common/handlers/base.py
flootty/floo/common/handlers/credentials.py
flootty/floo/common/handlers/floo_handler.py
flootty/floo/common/handlers/tcp_server.py
flootty/floo/common/lib/__init__.py
flootty/floo/common/lib/diff_match_patch.py
flootty/floo/common/lib/dmp_monkey.py
flootty/floo/common/protocols/__init__.py
flootty/floo/common/protocols/base.py
flootty/floo/common/protocols/floo_proto.py
flootty/floo/common/protocols/no_reconnect.py
flootty/floo/common/protocols/proxy.py
flootty/floo/common/protocols/tcp_server.py
Flootty-3.3.0.dist-info/LICENSE
Flootty-3.3.0.dist-info/METADATA
Flootty-3.3.0.dist-info/NOTICE
Flootty-3.3.0.dist-info/WHEEL
Flootty-3.3.0.dist-info/entry_points.txt
Flootty-3.3.0.dist-info/top_level.txt
Flootty-3.3.0.dist-info/RECORD
