Metadata-Version: 2.1
Name: Flootty
Version: 3.3.0
Summary: Floobits collaborative terminal
Home-page: https://floobits.com/
Author: Floobits
Author-email: info@floobits.com
License: Apache2
Platform: UNKNOWN
Classifier: Development Status :: 5 - Production/Stable
Classifier: Environment :: Console
Classifier: Intended Audience :: Developers
Classifier: License :: OSI Approved :: Apache Software License
Classifier: Topic :: Terminals
Classifier: Topic :: Utilities
License-File: LICENSE
License-File: NOTICE
